{
  "string": [
    {
      "name": "app_name",
      "value": "簡易相簿"
    },
    {
      "name": "app_launcher_name",
      "value": "相簿"
    },
    {
      "name": "edit",
      "value": "編輯"
    },
    {
      "name": "open_camera",
      "value": "開啟相機"
    },
    {
      "name": "hidden",
      "value": "(隱藏)"
    },
    {
      "name": "excluded",
      "value": "(已排除)"
    },
    {
      "name": "pin_folder",
      "value": "釘選資料夾"
    },
    {
      "name": "unpin_folder",
      "value": "取消釘選資料夾"
    },
    {
      "name": "pin_to_the_top",
      "value": "釘選在頂端"
    },
    {
      "name": "show_all",
      "value": "顯示全部資料夾內容"
    },
    {
      "name": "all_folders",
      "value": "全部資料夾"
    },
    {
      "name": "folder_view",
      "value": "切換成資料夾檢視"
    },
    {
      "name": "other_folder",
      "value": "其他資料夾"
    },
    {
      "name": "show_on_map",
      "value": "在地圖上顯示"
    },
    {
      "name": "unknown_location",
      "value": "未知的位置"
    },
    {
      "name": "volume",
      "value": "音量"
    },
    {
      "name": "brightness",
      "value": "亮度"
    },
    {
      "name": "lock_orientation",
      "value": "鎖定方向"
    },
    {
      "name": "unlock_orientation",
      "value": "解除鎖定方向"
    },
    {
      "name": "change_orientation",
      "value": "改變方向"
    },
    {
      "name": "force_portrait",
      "value": "強制直向"
    },
    {
      "name": "force_landscape",
      "value": "強制橫向"
    },
    {
      "name": "use_default_orientation",
      "value": "使用預設方向"
    },
    {
      "name": "fix_date_taken",
      "value": "修復拍攝日期數值"
    },
    {
      "name": "fixing",
      "value": "修復中…"
    },
    {
      "name": "dates_fixed_successfully",
      "value": "日期修復成功"
    },
    {
      "name": "no_date_takens_found",
      "value": "未發現拍攝日期數值"
    },
    {
      "name": "share_resized",
      "value": "分享調整大小的版本"
    },
    {
      "name": "switch_to_file_search",
      "value": "檔案搜尋目標切換成全部的可見資料夾"
    },
    {
      "name": "set_as_default_folder",
      "value": "設為預設資料夾"
    },
    {
      "name": "unset_as_default_folder",
      "value": "取消設為預設資料夾"
    },
    {
      "name": "reorder_by_dragging",
      "value": "透過拖曳來重新排序資料夾"
    },
    {
      "name": "reorder_by_dragging_pro",
      "value": "透過拖曳來重新排序資料夾 (專業版)"
    },
    {
      "name": "restore_to_path",
      "value": "還原到「%s」"
    },
    {
      "name": "filter_media",
      "value": "篩選媒體檔案"
    },
    {
      "name": "images",
      "value": "圖片"
    },
    {
      "name": "videos",
      "value": "影片"
    },
    {
      "name": "gifs",
      "value": "GIF"
    },
    {
      "name": "raw_images",
      "value": "RAW圖檔"
    },
    {
      "name": "svgs",
      "value": "SVG"
    },
    {
      "name": "portraits",
      "value": "人像"
    },
    {
      "name": "no_media_with_filters",
      "value": "選擇的篩選條件未發現媒體檔案。"
    },
    {
      "name": "change_filters_underlined",
      "value": "更改篩選條件"
    },
    {
      "name": "hide_folder_description",
      "value": "啟用此功能將會在選定資料夾中建立「.nomedia」檔案，使該資料夾及其所有子資料夾被隱藏。如果您想查看這些隱藏的資料夾，可以在設定中選擇「顯示隱藏項目」的選項。是否繼續？"
    },
    {
      "name": "exclude_folder_description",
      "value": "此資料夾與子資料夾將只會都從簡易相簿中排除。您可以在設定中進行管理。"
    },
    {
      "name": "exclude_folder_parent",
      "value": "是否排除上層資料夾？"
    },
    {
      "name": "excluded_activity_placeholder",
      "value": "[排除資料夾]只會將選擇的資料夾與子資料夾一起從簡易相簿中隱藏，它們仍會出現在其他應用程式中。\r\n\\n\r\n\\n如果您要在其他應用程式中也隱藏，請使用[隱藏]功能。"
    },
    {
      "name": "hidden_folders",
      "value": "隱藏資料夾"
    },
    {
      "name": "manage_hidden_folders",
      "value": "管理隱藏資料夾"
    },
    {
      "name": "hidden_folders_placeholder",
      "value": "看來沒有以「.nomedia」檔案來隱藏的資料夾。"
    },
    {
      "name": "hidden_all_files",
      "value": "為了讓您能夠查看隱藏的檔案，請務必開放「所有檔案存取」的權限給此應用程式，否則將無法正常使用。"
    },
    {
      "name": "cant_unhide_folder",
      "value": "若資料夾或其母資料夾的名稱前方有「.」，該資料夾將會被隱藏，而此情況下不能直接取消隱藏。您需要改變資料夾名稱以移除前方的「.」。"
    },
    {
      "name": "include_folders",
      "value": "包含資料夾"
    },
    {
      "name": "manage_included_folders",
      "value": "管理包含資料夾"
    },
    {
      "name": "add_folder",
      "value": "增加資料夾"
    },
    {
      "name": "included_activity_placeholder",
      "value": "如果您擁有一些含有媒體文件但未被應用程式識別的資料夾，您可以手動於此新增它們。\r\n\\n\r\n\\n此處新增的項目不會將其他資料夾排除在外。"
    },
    {
      "name": "no_media_add_included",
      "value": "未發現媒體檔案。您可以手動加入包含媒體檔案的資料夾來解決。"
    },
    {
      "name": "resize_and_save",
      "value": "縮放所選區域並儲存"
    },
    {
      "name": "width",
      "value": "寬度"
    },
    {
      "name": "height",
      "value": "高度"
    },
    {
      "name": "keep_aspect_ratio",
      "value": "保持長寬比"
    },
    {
      "name": "invalid_values",
      "value": "請輸入有效的解析度"
    },
    {
      "name": "resize_multiple_images",
      "value": "批量調整圖片大小"
    },
    {
      "name": "resize_factor",
      "value": "調整比例"
    },
    {
      "name": "resize_factor_info",
      "value": "請將圖片大小調整至指定百分比，數值範圍為 10 到 90。"
    },
    {
      "name": "resize_factor_error",
      "value": "請輸入 10 到 90 之間的數值"
    },
    {
      "name": "images_resized_successfully",
      "value": "圖片調整大小成功"
    },
    {
      "name": "editor",
      "value": "編輯器"
    },
    {
      "name": "basic_editor",
      "value": "基礎編輯器"
    },
    {
      "name": "advanced_editor",
      "value": "進階編輯器"
    },
    {
      "name": "rotate",
      "value": "旋轉"
    },
    {
      "name": "invalid_image_path",
      "value": "無效的圖片路徑"
    },
    {
      "name": "invalid_video_path",
      "value": "無效的影片路徑"
    },
    {
      "name": "image_editing_failed",
      "value": "圖片編輯失敗"
    },
    {
      "name": "video_editing_failed",
      "value": "影片編輯失敗"
    },
    {
      "name": "image_editing_cancelled",
      "value": "圖片編輯取消"
    },
    {
      "name": "video_editing_cancelled",
      "value": "影片編輯取消"
    },
    {
      "name": "file_edited_successfully",
      "value": "檔案編輯成功"
    },
    {
      "name": "image_edited_successfully",
      "value": "圖片編輯成功"
    },
    {
      "name": "video_edited_successfully",
      "value": "影片編輯成功"
    },
    {
      "name": "edit_image_with",
      "value": "編輯圖片:"
    },
    {
      "name": "edit_video_with",
      "value": "編輯影片:"
    },
    {
      "name": "no_image_editor_found",
      "value": "找不到圖片編輯器"
    },
    {
      "name": "no_video_editor_found",
      "value": "找不到影片編輯器"
    },
    {
      "name": "unknown_file_location",
      "value": "未知的檔案位置"
    },
    {
      "name": "error_saving_file",
      "value": "無法覆蓋原始檔案"
    },
    {
      "name": "rotate_left",
      "value": "向左轉"
    },
    {
      "name": "rotate_right",
      "value": "向右轉"
    },
    {
      "name": "rotate_one_eighty",
      "value": "旋轉180º"
    },
    {
      "name": "transform",
      "value": "變形"
    },
    {
      "name": "crop",
      "value": "裁切"
    },
    {
      "name": "draw",
      "value": "繪畫"
    },
    {
      "name": "flip",
      "value": "翻轉"
    },
    {
      "name": "flip_horizontally",
      "value": "水平翻轉"
    },
    {
      "name": "flip_vertically",
      "value": "垂直翻轉"
    },
    {
      "name": "free_aspect_ratio",
      "value": "自由"
    },
    {
      "name": "other_aspect_ratio",
      "value": "其它"
    },
    {
      "name": "simple_wallpaper",
      "value": "簡易桌布"
    },
    {
      "name": "set_as_wallpaper",
      "value": "設為桌布"
    },
    {
      "name": "set_as_wallpaper_failed",
      "value": "設為桌布失敗"
    },
    {
      "name": "set_as_wallpaper_with",
      "value": "用其他程式設為桌布:"
    },
    {
      "name": "setting_wallpaper",
      "value": "桌布設定中…"
    },
    {
      "name": "wallpaper_set_successfully",
      "value": "成功設為桌布"
    },
    {
      "name": "portrait_aspect_ratio",
      "value": "直向長寬比"
    },
    {
      "name": "landscape_aspect_ratio",
      "value": "橫向長寬比"
    },
    {
      "name": "home_screen",
      "value": "主畫面"
    },
    {
      "name": "lock_screen",
      "value": "鎖定畫面"
    },
    {
      "name": "home_and_lock_screen",
      "value": "主畫面及鎖定畫面"
    },
    {
      "name": "allow_changing_aspect_ratio",
      "value": "允許變更長寬比"
    },
    {
      "name": "slideshow",
      "value": "投影片"
    },
    {
      "name": "interval",
      "value": "間隔"
    },
    {
      "name": "include_photos",
      "value": "包含照片"
    },
    {
      "name": "include_videos",
      "value": "包含影片"
    },
    {
      "name": "include_gifs",
      "value": "包含GIF"
    },
    {
      "name": "random_order",
      "value": "隨機順序"
    },
    {
      "name": "move_backwards",
      "value": "反向播放"
    },
    {
      "name": "loop_slideshow",
      "value": "投影片循環"
    },
    {
      "name": "animation",
      "value": "動畫"
    },
    {
      "name": "no_animation",
      "value": "無"
    },
    {
      "name": "fade",
      "value": "漸變"
    },
    {
      "name": "slide",
      "value": "滑動"
    },
    {
      "name": "slideshow_ended",
      "value": "投影片結束"
    },
    {
      "name": "no_media_for_slideshow",
      "value": "找不到投影片的媒體檔案"
    },
    {
      "name": "group_direct_subfolders",
      "value": "歸類子資料夾"
    },
    {
      "name": "group_by",
      "value": "歸類"
    },
    {
      "name": "do_not_group_files",
      "value": "不歸類檔案"
    },
    {
      "name": "by_folder",
      "value": "資料夾"
    },
    {
      "name": "by_last_modified",
      "value": "最後修改"
    },
    {
      "name": "by_last_modified_daily",
      "value": "最後修改 (按日)"
    },
    {
      "name": "by_last_modified_monthly",
      "value": "最後修改 (按月)"
    },
    {
      "name": "by_date_taken",
      "value": "拍攝日期"
    },
    {
      "name": "by_date_taken_daily",
      "value": "拍攝日期 (按日)"
    },
    {
      "name": "by_date_taken_monthly",
      "value": "拍攝日期 (按月)"
    },
    {
      "name": "by_file_type",
      "value": "檔案類型"
    },
    {
      "name": "by_extension",
      "value": "副檔名"
    },
    {
      "name": "show_file_count_section_header",
      "value": "於分段標題顯示檔案數量"
    },
    {
      "name": "grouping_and_sorting",
      "value": "請注意，歸類和排序兩者是獨立的"
    },
    {
      "name": "folder_on_widget",
      "value": "在小工具顯示資料夾:"
    },
    {
      "name": "show_folder_name",
      "value": "顯示資料夾名稱"
    },
    {
      "name": "autoplay_videos",
      "value": "自動播放影片"
    },
    {
      "name": "remember_last_video_position",
      "value": "記住影片上次播放位置"
    },
    {
      "name": "loop_videos",
      "value": "影片循環播放"
    },
    {
      "name": "animate_gifs",
      "value": "縮圖顯示GIF動畫"
    },
    {
      "name": "max_brightness",
      "value": "瀏覽時將亮度設為最亮"
    },
    {
      "name": "crop_thumbnails",
      "value": "縮圖裁剪成正方形"
    },
    {
      "name": "show_thumbnail_video_duration",
      "value": "顯示影片長度"
    },
    {
      "name": "screen_rotation_by",
      "value": "全螢幕時旋轉方向"
    },
    {
      "name": "screen_rotation_system_setting",
      "value": "系統設定方向"
    },
    {
      "name": "screen_rotation_device_rotation",
      "value": "裝置實際方向"
    },
    {
      "name": "screen_rotation_aspect_ratio",
      "value": "圖片長寬比"
    },
    {
      "name": "black_background_at_fullscreen",
      "value": "全螢幕時將背景設成黑色"
    },
    {
      "name": "scroll_thumbnails_horizontally",
      "value": "橫向滑動縮圖"
    },
    {
      "name": "hide_system_ui_at_fullscreen",
      "value": "全螢幕時自動隱藏系統介面"
    },
    {
      "name": "delete_empty_folders",
      "value": "刪除資料夾內所有檔案後自動刪除空資料夾"
    },
    {
      "name": "allow_photo_gestures",
      "value": "使用上下手勢來控制相片的亮度"
    },
    {
      "name": "allow_video_gestures",
      "value": "使用上下手勢來控制影片的音量和亮度"
    },
    {
      "name": "show_media_count",
      "value": "在主畫面顯示資料夾內的媒體檔案數量"
    },
    {
      "name": "show_extended_details",
      "value": "全螢幕時顯示詳細資訊"
    },
    {
      "name": "manage_extended_details",
      "value": "管理詳細資訊"
    },
    {
      "name": "one_finger_zoom",
      "value": "全螢幕時使用單指縮放"
    },
    {
      "name": "allow_instant_change",
      "value": "輕觸螢幕邊緣來快速切換媒體檔案"
    },
    {
      "name": "allow_deep_zooming_images",
      "value": "深度縮放圖片"
    },
    {
      "name": "hide_extended_details",
      "value": "狀態欄隱藏時，同時隱藏詳細資訊"
    },
    {
      "name": "show_at_bottom",
      "value": "在螢幕底部顯示一些操作按鈕"
    },
    {
      "name": "show_recycle_bin",
      "value": "在資料夾畫面顯示回收桶"
    },
    {
      "name": "deep_zoomable_images",
      "value": "可深度縮放的圖片"
    },
    {
      "name": "show_highest_quality",
      "value": "以最高品質顯示圖片"
    },
    {
      "name": "show_recycle_bin_last",
      "value": "回收桶顯示在主畫面最後一項"
    },
    {
      "name": "allow_down_gesture",
      "value": "以下滑手勢關閉全螢幕檢視"
    },
    {
      "name": "allow_one_to_one_zoom",
      "value": "按兩下螢幕兩次來1:1縮放"
    },
    {
      "name": "open_videos_on_separate_screen",
      "value": "總是用新的水平手勢在獨立畫面開啟影片"
    },
    {
      "name": "show_notch",
      "value": "如果可以，顯示螢幕凹口"
    },
    {
      "name": "allow_rotating_gestures",
      "value": "使用手勢來旋轉圖片"
    },
    {
      "name": "file_loading_priority",
      "value": "檔案讀取優先權"
    },
    {
      "name": "speed",
      "value": "速度"
    },
    {
      "name": "compromise",
      "value": "妥協"
    },
    {
      "name": "avoid_showing_invalid_files",
      "value": "避免顯示無效的檔案"
    },
    {
      "name": "show_image_file_types",
      "value": "顯示圖片檔案類型"
    },
    {
      "name": "allow_zooming_videos",
      "value": "點兩下螢幕來縮放影片"
    },
    {
      "name": "folder_thumbnail_style",
      "value": "資料夾縮圖樣式"
    },
    {
      "name": "file_thumbnail_style",
      "value": "檔案縮圖樣式"
    },
    {
      "name": "mark_favorite_items",
      "value": "標記我的最愛"
    },
    {
      "name": "thumbnail_spacing",
      "value": "縮圖的間隔"
    },
    {
      "name": "show_file_count_line",
      "value": "獨立一行顯示檔案數量"
    },
    {
      "name": "show_file_count_brackets",
      "value": "在括號內顯示檔案數量"
    },
    {
      "name": "show_file_count_none",
      "value": "不顯示檔案數量"
    },
    {
      "name": "limit_folder_title",
      "value": "資料夾名稱最長只顯示一行"
    },
    {
      "name": "square",
      "value": "方形"
    },
    {
      "name": "rounded_corners",
      "value": "圓角"
    },
    {
      "name": "export_favorite_paths",
      "value": "匯出我的最愛"
    },
    {
      "name": "import_favorite_paths",
      "value": "匯入我的最愛"
    },
    {
      "name": "paths_imported_successfully",
      "value": "路徑匯入成功"
    },
    {
      "name": "media_management_prompt",
      "value": "為了確保所有檔案操作都能可靠地運作，請將此 app 設為裝置設定中的媒體管理 app。"
    },
    {
      "name": "password_protect_excluded",
      "value": "密碼保護以隱藏特定資料夾"
    },
    {
      "name": "media_management_manual",
      "value": "出錯了，請至裝置的設定 - 應用程式（和通知） - 特殊應用程式存取權 - 媒體管理應用程式，允許本 app 管理媒體。"
    },
    {
      "name": "media_management_note",
      "value": "若重新導向未順利運作，請至裝置的設定 - 應用程式（和通知） - 特殊應用程式存取權 - 媒體管理應用程式，允許本 app 管理媒體。"
    },
    {
      "name": "media_management_alternative",
      "value": "如果您不想這麼做，也可以進入您的裝置設定 - 應用程式 - 特殊應用程式存取 - 媒體管理應用程式，並允許此應用程式管理媒體。"
    },
    {
      "name": "alternative_media_access",
      "value": "或者，您只能允許存取媒體檔案。但在這種情況下，您將無法處理隱藏檔案。"
    },
    {
      "name": "media_only",
      "value": "僅媒體"
    },
    {
      "name": "all_files",
      "value": "所有檔案"
    },
    {
      "name": "search_all_files",
      "value": "在主畫面搜尋所有檔案，而非資料夾"
    },
    {
      "name": "show_all_folders",
      "value": "顯示一個選單按鈕，快速切換「顯示所有資料夾內容」"
    },
    {
      "name": "thumbnails",
      "value": "縮圖"
    },
    {
      "name": "fullscreen_media",
      "value": "全螢幕媒體檔案"
    },
    {
      "name": "extended_details",
      "value": "詳細資訊"
    },
    {
      "name": "bottom_actions",
      "value": "底部操作"
    },
    {
      "name": "manage_bottom_actions",
      "value": "管理要顯示的底部操作"
    },
    {
      "name": "toggle_favorite",
      "value": "我的最愛"
    },
    {
      "name": "toggle_file_visibility",
      "value": "檔案顯示"
    },
    {
      "name": "pesdk_transform_button_freeCrop",
      "value": "自訂"
    },
    {
      "name": "pesdk_transform_button_resetCrop",
      "value": "重置"
    },
    {
      "name": "pesdk_transform_button_squareCrop",
      "value": "正方形"
    },
    {
      "name": "pesdk_transform_title_name",
      "value": "變形"
    },
    {
      "name": "pesdk_filter_title_name",
      "value": "濾鏡"
    },
    {
      "name": "pesdk_filter_asset_none",
      "value": "無"
    },
    {
      "name": "pesdk_adjustments_title_name",
      "value": "調整"
    },
    {
      "name": "pesdk_adjustments_button_shadowTool",
      "value": "暗部"
    },
    {
      "name": "pesdk_adjustments_button_exposureTool",
      "value": "曝光"
    },
    {
      "name": "pesdk_adjustments_button_highlightTool",
      "value": "高光"
    },
    {
      "name": "pesdk_adjustments_button_brightnessTool",
      "value": "亮度"
    },
    {
      "name": "pesdk_adjustments_button_contrastTool",
      "value": "對比"
    },
    {
      "name": "pesdk_adjustments_button_saturationTool",
      "value": "飽和度"
    },
    {
      "name": "pesdk_adjustments_button_clarityTool",
      "value": "清晰度"
    },
    {
      "name": "pesdk_adjustments_button_gammaTool",
      "value": "Gamma"
    },
    {
      "name": "pesdk_adjustments_button_blacksTool",
      "value": "黑色"
    },
    {
      "name": "pesdk_adjustments_button_whitesTool",
      "value": "白色"
    },
    {
      "name": "pesdk_adjustments_button_temperatureTool",
      "value": "色溫"
    },
    {
      "name": "pesdk_adjustments_button_sharpnessTool",
      "value": "銳利度"
    },
    {
      "name": "pesdk_adjustments_button_reset",
      "value": "重置"
    },
    {
      "name": "pesdk_focus_title_name",
      "value": "聚焦"
    },
    {
      "name": "pesdk_focus_title_disabled",
      "value": "無"
    },
    {
      "name": "pesdk_focus_button_radial",
      "value": "放射"
    },
    {
      "name": "pesdk_focus_button_linear",
      "value": "線性"
    },
    {
      "name": "pesdk_focus_button_mirrored",
      "value": "鏡像"
    },
    {
      "name": "pesdk_focus_button_gaussian",
      "value": "高斯"
    },
    {
      "name": "pesdk_text_title_input",
      "value": "Add text"
    },
    {
      "name": "pesdk_text_title_name",
      "value": "文字"
    },
    {
      "name": "pesdk_text_title_options",
      "value": "文字選項"
    },
    {
      "name": "pesdk_text_title_textColor",
      "value": "文字顏色"
    },
    {
      "name": "pesdk_text_title_font",
      "value": "字型"
    },
    {
      "name": "pesdk_text_button_add",
      "value": "新增"
    },
    {
      "name": "pesdk_text_button_edit",
      "value": "編輯"
    },
    {
      "name": "pesdk_text_button_straighten",
      "value": "拉伸"
    },
    {
      "name": "pesdk_text_button_font",
      "value": "字型"
    },
    {
      "name": "pesdk_text_button_color",
      "value": "顏色"
    },
    {
      "name": "pesdk_text_button_backgroundColor",
      "value": "背景顏色"
    },
    {
      "name": "pesdk_text_button_alignment",
      "value": "對齊"
    },
    {
      "name": "pesdk_text_button_bringToFront",
      "value": "移到最上層"
    },
    {
      "name": "pesdk_text_button_delete",
      "value": "刪除"
    },
    {
      "name": "pesdk_text_text_editTextPlaceholder",
      "value": "你的文字"
    },
    {
      "name": "pesdk_brush_title_name",
      "value": "筆刷"
    },
    {
      "name": "pesdk_brush_button_color",
      "value": "顏色"
    },
    {
      "name": "pesdk_brush_button_size",
      "value": "尺寸"
    },
    {
      "name": "pesdk_brush_button_hardness",
      "value": "硬度"
    },
    {
      "name": "pesdk_brush_button_bringToFront",
      "value": "移到最上層"
    },
    {
      "name": "pesdk_brush_button_delete",
      "value": "刪除"
    },
    {
      "name": "pesdk_brush_title_brushColor",
      "value": "筆刷顏色"
    },
    {
      "name": "pesdk_editor_title_name",
      "value": "編輯器"
    },
    {
      "name": "pesdk_editor_title_closeEditorAlert",
      "value": "關閉編輯器？"
    },
    {
      "name": "pesdk_editor_text_closeEditorAlert",
      "value": "確定捨棄所做的編輯？"
    },
    {
      "name": "pesdk_editor_button_closeEditorAlertConfirmation",
      "value": "是"
    },
    {
      "name": "pesdk_editor_button_closeEditorAlertCancelation",
      "value": "否"
    },
    {
      "name": "pesdk_editor_cancel",
      "value": "取消"
    },
    {
      "name": "pesdk_editor_accept",
      "value": "接受"
    },
    {
      "name": "pesdk_editor_save",
      "value": "儲存"
    },
    {
      "name": "pesdk_editor_text_exportProgressUnknown",
      "value": "輸出中…"
    },
    {
      "name": "pesdk_editor_text_exportProgress",
      "value": "正在匯出 %s。"
    },
    {
      "name": "pesdk_sticker_title_name",
      "value": "貼圖"
    },
    {
      "name": "pesdk_sticker_title_color",
      "value": "貼圖顏色"
    },
    {
      "name": "pesdk_sticker_title_options",
      "value": "貼圖選項"
    },
    {
      "name": "pesdk_sticker_button_add",
      "value": "新增"
    },
    {
      "name": "pesdk_sticker_button_color",
      "value": "顏色"
    },
    {
      "name": "pesdk_sticker_button_delete",
      "value": "刪除"
    },
    {
      "name": "pesdk_sticker_button_bringToFront",
      "value": "移到最上層"
    },
    {
      "name": "pesdk_sticker_button_straighten",
      "value": "矯正"
    },
    {
      "name": "pesdk_sticker_button_replace",
      "value": "更改"
    },
    {
      "name": "pesdk_sticker_button_opacity",
      "value": "不透明度"
    },
    {
      "name": "pesdk_sticker_button_contrast",
      "value": "對比"
    },
    {
      "name": "pesdk_sticker_button_saturation",
      "value": "飽和度"
    },
    {
      "name": "pesdk_sticker_button_brightness",
      "value": "亮度"
    },
    {
      "name": "pesdk_sticker_category_name_custom",
      "value": "上傳"
    },
    {
      "name": "pesdk_overlay_title_name",
      "value": "覆蓋"
    },
    {
      "name": "pesdk_overlay_button_blendModeNormal",
      "value": "Normal"
    },
    {
      "name": "pesdk_overlay_button_blendModeDarken",
      "value": "變暗"
    },
    {
      "name": "pesdk_overlay_button_blendModeScreen",
      "value": "Screen"
    },
    {
      "name": "pesdk_overlay_button_blendModeOverlay",
      "value": "覆蓋"
    },
    {
      "name": "pesdk_overlay_button_blendModeLighten",
      "value": "變亮"
    },
    {
      "name": "pesdk_overlay_button_blendModeMultiply",
      "value": "色彩增值"
    },
    {
      "name": "pesdk_overlay_button_blendModeColorBurn",
      "value": "加深顏色"
    },
    {
      "name": "pesdk_overlay_button_blendModeSoftLight",
      "value": "柔光"
    },
    {
      "name": "pesdk_overlay_button_blendModeHardLight",
      "value": "實光"
    },
    {
      "name": "pesdk_overlay_asset_none",
      "value": "無"
    },
    {
      "name": "pesdk_overlay_asset_golden",
      "value": "金色"
    },
    {
      "name": "pesdk_overlay_asset_lightleak1",
      "value": "光漏 1"
    },
    {
      "name": "pesdk_overlay_asset_mosaic",
      "value": "馬賽克"
    },
    {
      "name": "pesdk_overlay_asset_paper",
      "value": "紙質"
    },
    {
      "name": "pesdk_overlay_asset_rain",
      "value": "雨"
    },
    {
      "name": "pesdk_overlay_asset_vintage",
      "value": "Vintage"
    },
    {
      "name": "pesdk_common_button_flipH",
      "value": "水平翻轉"
    },
    {
      "name": "pesdk_common_button_flipV",
      "value": "垂直翻轉"
    },
    {
      "name": "pesdk_common_button_undo",
      "value": "復原"
    },
    {
      "name": "pesdk_common_button_redo",
      "value": "取消復原"
    },
    {
      "name": "pesdk_common_title_colorPicker",
      "value": "顏色挑選器"
    },
    {
      "name": "pesdk_common_title_transparentColor",
      "value": "透明"
    },
    {
      "name": "pesdk_common_title_whiteColor",
      "value": "白色"
    },
    {
      "name": "pesdk_common_title_grayColor",
      "value": "灰色"
    },
    {
      "name": "pesdk_common_title_blackColor",
      "value": "黑色"
    },
    {
      "name": "pesdk_common_title_lightBlueColor",
      "value": "淺藍"
    },
    {
      "name": "pesdk_common_title_blueColor",
      "value": "藍色"
    },
    {
      "name": "pesdk_common_title_purpleColor",
      "value": "紫色"
    },
    {
      "name": "pesdk_common_title_orchidColor",
      "value": "淡紫"
    },
    {
      "name": "pesdk_common_title_pinkColor",
      "value": "粉紅"
    },
    {
      "name": "pesdk_common_title_redColor",
      "value": "紅色"
    },
    {
      "name": "pesdk_common_title_orangeColor",
      "value": "橘色"
    },
    {
      "name": "pesdk_common_title_goldColor",
      "value": "金色"
    },
    {
      "name": "pesdk_common_title_yellowColor",
      "value": "黃色"
    },
    {
      "name": "pesdk_common_title_oliveColor",
      "value": "橄欖"
    },
    {
      "name": "pesdk_common_title_greenColor",
      "value": "綠色"
    },
    {
      "name": "pesdk_common_title_aquamarinColor",
      "value": "藍綠"
    },
    {
      "name": "pesdk_common_title_pipettableColor",
      "value": "顏色吸取器"
    },
    {
      "name": "vesdk_video_trim_title_name",
      "value": "修剪"
    },
    {
      "name": "faq_1_title",
      "value": "如何將簡易相簿設為裝置的預設相簿？"
    },
    {
      "name": "faq_1_text",
      "value": "首先開啟裝置的設定，在應用程式相關設定處找到目前的預設相簿。 選擇「預設為開啟」或類似的選項，然後按「清除預設值」。 之後開啟圖片或影片檔案時會出現選擇 APP 的畫面，此時即可將簡易相簿設為預設相簿。"
    },
    {
      "name": "faq_2_title",
      "value": "用密碼把這個 APP 上鎖後忘記密碼該怎麼辦？"
    },
    {
      "name": "faq_2_text",
      "value": "有兩種解決方法。一是重新安裝本 APP。一是在裝置的設定中找到本 APP，然後按「清除資料」（或「清除儲存空間」等類似的字眼），APP 的設定將會被重設，但不會移除任何媒體檔案。"
    },
    {
      "name": "faq_3_title",
      "value": "如何使某個相簿顯示在最頂端？"
    },
    {
      "name": "faq_3_text",
      "value": "長按該相簿，接著按圖釘圖示或選單中的「釘選在頂端」。您可以同時釘選數個相簿，它們將會依照預設排序方式排序。"
    },
    {
      "name": "faq_4_title",
      "value": "如何快轉影片？"
    },
    {
      "name": "faq_4_text",
      "value": "按兩下螢幕邊邊，或者按一下進度條旁邊的目前播放時間／影片時長文字。若您在設定中啟用了「總是用新的水平手勢在獨立畫面開啟影片」，則您也可以使用水平手勢快轉。"
    },
    {
      "name": "faq_5_title",
      "value": "「隱藏」與「排除」資料夾的差別是？"
    },
    {
      "name": "faq_5_text",
      "value": "「排除」只會使該資料夾在簡易相簿中隱藏；而「隱藏」則會影響整個系統，使其也會在其他的相簿 APP 中隱藏，其運作原理是在該資料夾中建立一個空的「.nomedia」檔案（您可使用任意檔案管理器移除此檔案）。另外，某些裝置不允許隱藏相片、螢幕擷圖、下載等資料夾。"
    },
    {
      "name": "faq_6_title",
      "value": "為何出現了音樂的封面圖或是貼圖的資料夾？"
    },
    {
      "name": "faq_6_text",
      "value": "有時候會出現一些異常的相簿。長按並點選排除可排除它們，在接下來的對話框選擇它們的上層資料夾的話，有機會避免相關的相簿出現。"
    },
    {
      "name": "faq_7_title",
      "value": "有個含有圖片的資料夾沒出現，抑或是沒有顯示所有項目時，該怎麼辦？"
    },
    {
      "name": "faq_7_text",
      "value": "可能有很多種原因，但解法很簡單。前往「設定」 -> 「管理包含資料夾」、按加號(+)、選擇該資料夾即可。"
    },
    {
      "name": "faq_8_title",
      "value": "如果只想顯示特定資料夾呢？"
    },
    {
      "name": "faq_8_text",
      "value": "如果只將某資料夾加入至「包含資料夾」的話，其他的資料夾並不會被自動排除。請前往「設定」->「管理排除資料夾」、將根資料夾「/」排除，並在「設定」->「管理包含資料夾」中加入欲顯示的資料夾。 這樣就只會顯示所選的資料夾，因為排除與包含都是遞迴的，所以若某資料夾同時被包含及排除，其將會顯示。"
    },
    {
      "name": "faq_10_title",
      "value": "這個 APP 可以裁剪圖片嗎？"
    },
    {
      "name": "faq_10_text",
      "value": "可以，在編輯器中拖動圖片的角落即可裁剪圖片。對縮圖長按並選擇編輯，或者在全螢幕檢視時選擇編輯皆可進入編輯器。"
    },
    {
      "name": "faq_11_title",
      "value": "有辦法分類縮圖嗎？"
    },
    {
      "name": "faq_11_text",
      "value": "可以，在檢視縮圖時使用選單中的「歸類」即可，有多種分類方式可供選擇，包含拍攝日期等。若使用了「資料夾內容全部顯示」功能，則也可以依資料夾來分類。"
    },
    {
      "name": "faq_12_title",
      "value": "依照拍攝日期的排序好像排得不太對，要怎麼修正？"
    },
    {
      "name": "faq_12_text",
      "value": "很有可能是因為檔案是從其他地方複製過來的。選擇縮圖並選擇「修復拍攝日期數值」即可修正。"
    },
    {
      "name": "faq_13_title",
      "value": "看到圖片上出現了色帶問題，要如何改善畫質？"
    },
    {
      "name": "faq_13_text",
      "value": "目前顯示圖片的方式在大多數情況下都能正常運作，但若想要更好的畫質，可以啟用「設定」->「可深度縮放的圖片」段落中的「以最高品質顯示圖片」。"
    },
    {
      "name": "faq_14_title",
      "value": "如何取消隱藏檔案／資料夾？"
    },
    {
      "name": "faq_14_text",
      "value": "按主畫面選單中的「暫時顯示隱藏的檔案」或設定中的「顯示隱藏的項目」就能看到隱藏的項目。若要取消隱藏，長按並選擇「取消隱藏」即可。資料夾隱藏的原理是在其內新增一個「.nomedia」檔案，因此可用任意檔案管理器將其刪除。檔案／資料夾是以遞迴的方式被隱藏的，因此若某資料夾被隱藏，其子資料夾也會被隱藏。若要取消隱藏子資料夾，其上層資料夾需先被取消隱藏。"
    },
    {
      "name": "faq_15_title",
      "value": "這個 APP 怎麼佔用了這麼多空間？"
    },
    {
      "name": "faq_15_text",
      "value": "APP 快取最高會佔用 250MB，來讓圖片載入得更快。如果本 APP 佔用了超過 250MB 的空間，很有可能是因為有檔案在回收桶裡，這些檔案也會算在 APP 佔用的空間上。您可以開啟回收桶並刪除所有檔案，或是從設定中清空它。檔案被丟入回收桶 30 天後將會自動被刪除。"
    },
    {
      "name": "faq_16_title",
      "value": "檔案／資料夾隱藏怎麼了？為什麼我看不到隱藏的項目了？"
    },
    {
      "name": "faq_16_text",
      "value": "自 Android 11 開始，因系統限制，無法隱藏或解除隱藏檔案或資料夾，也無法在相簿 app 中看到已隱藏的項目。請使用檔案管理程式達成上述操作。"
    },
    {
      "name": "faq_16_text_extra",
      "value": "或者，您也可以通過您的裝置設定授予此相簿存取所有檔案的權限，這將允許我們顯示隱藏項目並使檔案操作更為可靠。"
    },
    {
      "name": "faq_17_title",
      "value": "為什麼不能再包含缺漏的資料夾了？"
    },
    {
      "name": "faq_17_text",
      "value": "因 Android 11 的系統變更，這項功能無法再運作。app 沒辦法瀏覽實際的資料夾，而是透過所謂的 MediaStorage 來擷取資料。"
    },
    {
      "name": "faq_18_title",
      "value": "為什麼我在播放影片時看到廣告？"
    },
    {
      "name": "faq_18_text",
      "value": "我們的應用程式完全沒有廣告。如果您在播放影片時看到它們，那麼您一定是在使用其他應用程式的影片播放器。嘗試在裝置設定中找到您的預設影片播放器，然後對其進行清除其預設值。下次您嘗試播放影片時，系統會提示您選擇應用程式，您可以在此選擇您想要使用的影片播放器。"
    }
  ]
}
